clup/__init__.py
clup/clup.py
clup-0.1.0.dist-info/LICENSE
clup-0.1.0.dist-info/METADATA
clup-0.1.0.dist-info/WHEEL
clup-0.1.0.dist-info/entry_points.txt
clup-0.1.0.dist-info/RECORD
