Metadata-Version: 2.1
Name: clup
Version: 0.1.0
Summary: 
Author: Almaz Ilaletdinov
Author-email: a.ilaletdinov@yandex.ru
Requires-Python: >=3.9,<4.0
Classifier: Programming Language :: Python :: 3
Classifier: Programming Language :: Python :: 3.9
Classifier: Programming Language :: Python :: 3.10
Classifier: Programming Language :: Python :: 3.11
Classifier: Programming Language :: Python :: 3.12
